src/__init__.py
src/cli.py
src/aggregation/__init__.py
src/aggregation/daily_stats.py
src/aggregation/usage_limits.py
src/commands/__init__.py
src/commands/delete_usage.py
src/commands/export.py
src/commands/help.py
src/commands/init_container.py
src/commands/limits.py
src/commands/restore_backup.py
src/commands/stats.py
src/commands/status_bar.py
src/commands/update_usage.py
src/commands/usage.py
src/commands/remove/__init__.py
src/commands/remove/hooks.py
src/commands/remove/usage.py
src/commands/restore/__init__.py
src/commands/restore/usage.py
src/commands/setup/__init__.py
src/commands/setup/container.py
src/commands/setup/hooks.py
src/commands/update/__init__.py
src/commands/update/usage.py
src/config/__init__.py
src/config/settings.py
src/config/user_config.py
src/data/__init__.py
src/data/jsonl_parser.py
src/hooks/__init__.py
src/hooks/audio.py
src/hooks/audio_tts.py
src/hooks/awesome_hooks.py
src/hooks/manager.py
src/hooks/png.py
src/hooks/usage.py
src/hooks/scripts/audio_tts_hook.sh
src/hooks_data/bundler-standard.ts
src/hooks_data/file-name-consistency.sh
src/hooks_data/uv-standard.py
src/models/__init__.py
src/models/usage_record.py
src/storage/__init__.py
src/storage/snapshot_db.py
src/utils/__init__.py
src/utils/_system.py
src/utils/text_analysis.py
src/visualization/__init__.py
src/visualization/activity_graph.py
src/visualization/dashboard.py
src/visualization/export.py
src/visualization/usage_bars.py
claude_goblin-0.1.10.dist-info/METADATA
claude_goblin-0.1.10.dist-info/WHEEL
claude_goblin-0.1.10.dist-info/entry_points.txt
claude_goblin-0.1.10.dist-info/licenses/LICENSE
claude_goblin-0.1.10.dist-info/RECORD
