Metadata-Version: 2.4
Name: claude-goblin
Version: 0.1.10
Summary: Python CLI for Claude Code utilities and usage tracking/analytics
Project-URL: Homepage, https://github.com/data-goblin/claude-goblin
Project-URL: Repository, https://github.com/data-goblin/claude-goblin
Project-URL: Issues, https://github.com/data-goblin/claude-goblin/issues
Author: Kurt Buhler
License: MIT
License-File: LICENSE
Keywords: analytics,claude,claude-code,dashboard,tui,usage,visualization
Classifier: Development Status :: 4 - Beta
Classifier: Intended Audience :: Developers
Classifier: License :: OSI Approved :: MIT License
Classifier: Programming Language :: Python :: 3
Classifier: Programming Language :: Python :: 3.10
Classifier: Programming Language :: Python :: 3.11
Classifier: Programming Language :: Python :: 3.12
Classifier: Programming Language :: Python :: 3.13
Classifier: Topic :: Software Development :: Libraries :: Python Modules
Classifier: Topic :: Utilities
Requires-Python: >=3.10
Requires-Dist: rich>=13.7.0
Requires-Dist: rumps>=0.4.0; sys_platform == 'darwin'
Requires-Dist: typer>=0.9.0
Provides-Extra: export
Requires-Dist: cairosvg>=2.7.0; extra == 'export'
Requires-Dist: pillow>=10.0.0; extra == 'export'
